{
    "[26, 'easy', 'any']": {
        "Question_1": {
            "type": "boolean",
            "difficulty": "easy",
            "category": "Celebrities",
            "question": "Tupac Shakur died due to complications from being stabbed in 1996.",
            "correct_answer": "False",
            "incorrect_answers": [
                "True"
            ]
        },
        "Question_2": {
            "type": "multiple",
            "difficulty": "easy",
            "category": "Celebrities",
            "question": "By what name is Carlos Estevez better known? ",
            "correct_answer": "Charlie Sheen",
            "incorrect_answers": [
                "Ricky Martin",
                "Bruno Mars",
                "Joaquin Phoenix"
            ]
        },
        "Question_3": {
            "type": "multiple",
            "difficulty": "easy",
            "category": "Celebrities",
            "question": "Aubrey Graham is better known as",
            "correct_answer": "Drake",
            "incorrect_answers": [
                "Travis Scott",
                "Lil Wayne",
                "2 Chainz"
            ]
        },
        "Question_4": {
            "type": "multiple",
            "difficulty": "easy",
            "category": "Celebrities",
            "question": "Which celebrity announced his presidency in 2015?",
            "correct_answer": "Kanye West",
            "incorrect_answers": [
                "Donald Trump",
                "Leonardo DiCaprio",
                "Miley Cyrus"
            ]
        },
        "Question_5": {
            "type": "multiple",
            "difficulty": "easy",
            "category": "Celebrities",
            "question": "What was the cause of Marilyn Monroes suicide?",
            "correct_answer": "Drug Overdose",
            "incorrect_answers": [
                "Knife Attack",
                "House Fire",
                "Gunshot"
            ]
        },
        "Question_6": {
            "type": "multiple",
            "difficulty": "easy",
            "category": "Celebrities",
            "question": "By which name is Ramon Estevez better known as?",
            "correct_answer": "Martin Sheen",
            "incorrect_answers": [
                "Charlie Sheen",
                "Ramon Sheen",
                "Emilio Estevez"
            ]
        },
        "Question_7": {
            "type": "multiple",
            "difficulty": "easy",
            "category": "Celebrities",
            "question": "What does film maker Dan Bell typically focus his films on?",
            "correct_answer": "Abandoned Buildings and Dead Malls",
            "incorrect_answers": [
                "Historic Landmarks",
                "Action Films",
                "Documentaries "
            ]
        },
        "Question_8": {
            "type": "multiple",
            "difficulty": "easy",
            "category": "Celebrities",
            "question": "Neil Hamburger is played by which comedian?",
            "correct_answer": "Gregg Turkington",
            "incorrect_answers": [
                "Nathan Fielder",
                "Tim Heidecker",
                "Todd Glass"
            ]
        },
        "Question_9": {
            "type": "multiple",
            "difficulty": "easy",
            "category": "Celebrities",
            "question": "What was James Coburn's last film role before his death?",
            "correct_answer": "American Gun",
            "incorrect_answers": [
                "Monsters Inc",
                "Texas Rangers",
                "Snow Dogs"
            ]
        },
        "Question_10": {
            "type": "multiple",
            "difficulty": "easy",
            "category": "Celebrities",
            "question": "Gwyneth Paltrow has a daughter named...?",
            "correct_answer": "Apple",
            "incorrect_answers": [
                "Lily",
                "French",
                "Dakota"
            ]
        },
        "Question_11": {
            "type": "multiple",
            "difficulty": "easy",
            "category": "Celebrities",
            "question": "Named after a character he played in a 1969 film, what is the name of the ski resort in Utah that Robert Redford bought in 1968?",
            "correct_answer": "Sundance",
            "incorrect_answers": [
                "Woodward",
                "Turner",
                "Booker"
            ]
        },
        "Question_12": {
            "type": "boolean",
            "difficulty": "easy",
            "category": "Celebrities",
            "question": "Marilyn Monroe was born on July 1, 1926.",
            "correct_answer": "False",
            "incorrect_answers": [
                "True"
            ]
        },
        "Question_13": {
            "type": "multiple",
            "difficulty": "easy",
            "category": "Celebrities",
            "question": "Which actress married Michael Douglas in 2000?",
            "correct_answer": "Catherine Zeta-Jones",
            "incorrect_answers": [
                "Ruth Jones",
                "Pam Ferris",
                "Sara Sugarman"
            ]
        }
    },
    "[26, 'easy', 'multiple']": {
        "Question_1": {
            "type": "multiple",
            "difficulty": "easy",
            "category": "Celebrities",
            "question": "Aubrey Graham is better known as",
            "correct_answer": "Drake",
            "incorrect_answers": [
                "Travis Scott",
                "Lil Wayne",
                "2 Chainz"
            ]
        },
        "Question_2": {
            "type": "multiple",
            "difficulty": "easy",
            "category": "Celebrities",
            "question": "What was the cause of Marilyn Monroes suicide?",
            "correct_answer": "Drug Overdose",
            "incorrect_answers": [
                "Knife Attack",
                "House Fire",
                "Gunshot"
            ]
        },
        "Question_3": {
            "type": "multiple",
            "difficulty": "easy",
            "category": "Celebrities",
            "question": "Neil Hamburger is played by which comedian?",
            "correct_answer": "Gregg Turkington",
            "incorrect_answers": [
                "Nathan Fielder",
                "Tim Heidecker",
                "Todd Glass"
            ]
        },
        "Question_4": {
            "type": "multiple",
            "difficulty": "easy",
            "category": "Celebrities",
            "question": "What does film maker Dan Bell typically focus his films on?",
            "correct_answer": "Abandoned Buildings and Dead Malls",
            "incorrect_answers": [
                "Historic Landmarks",
                "Action Films",
                "Documentaries "
            ]
        },
        "Question_5": {
            "type": "multiple",
            "difficulty": "easy",
            "category": "Celebrities",
            "question": "Which celebrity announced his presidency in 2015?",
            "correct_answer": "Kanye West",
            "incorrect_answers": [
                "Donald Trump",
                "Leonardo DiCaprio",
                "Miley Cyrus"
            ]
        },
        "Question_6": {
            "type": "multiple",
            "difficulty": "easy",
            "category": "Celebrities",
            "question": "By which name is Ramon Estevez better known as?",
            "correct_answer": "Martin Sheen",
            "incorrect_answers": [
                "Charlie Sheen",
                "Ramon Sheen",
                "Emilio Estevez"
            ]
        },
        "Question_7": {
            "type": "multiple",
            "difficulty": "easy",
            "category": "Celebrities",
            "question": "Gwyneth Paltrow has a daughter named...?",
            "correct_answer": "Apple",
            "incorrect_answers": [
                "Lily",
                "French",
                "Dakota"
            ]
        },
        "Question_8": {
            "type": "multiple",
            "difficulty": "easy",
            "category": "Celebrities",
            "question": "By what name is Carlos Estevez better known? ",
            "correct_answer": "Charlie Sheen",
            "incorrect_answers": [
                "Ricky Martin",
                "Bruno Mars",
                "Joaquin Phoenix"
            ]
        },
        "Question_9": {
            "type": "multiple",
            "difficulty": "easy",
            "category": "Celebrities",
            "question": "Named after a character he played in a 1969 film, what is the name of the ski resort in Utah that Robert Redford bought in 1968?",
            "correct_answer": "Sundance",
            "incorrect_answers": [
                "Woodward",
                "Turner",
                "Booker"
            ]
        },
        "Question_10": {
            "type": "multiple",
            "difficulty": "easy",
            "category": "Celebrities",
            "question": "Which actress married Michael Douglas in 2000?",
            "correct_answer": "Catherine Zeta-Jones",
            "incorrect_answers": [
                "Ruth Jones",
                "Pam Ferris",
                "Sara Sugarman"
            ]
        },
        "Question_11": {
            "type": "multiple",
            "difficulty": "easy",
            "category": "Celebrities",
            "question": "What was James Coburn's last film role before his death?",
            "correct_answer": "American Gun",
            "incorrect_answers": [
                "Monsters Inc",
                "Texas Rangers",
                "Snow Dogs"
            ]
        }
    },
    "[26, 'easy', 'boolean']": {
        "Question_1": {
            "type": "boolean",
            "difficulty": "easy",
            "category": "Celebrities",
            "question": "Marilyn Monroe was born on July 1, 1926.",
            "correct_answer": "False",
            "incorrect_answers": [
                "True"
            ]
        },
        "Question_2": {
            "type": "boolean",
            "difficulty": "easy",
            "category": "Celebrities",
            "question": "Tupac Shakur died due to complications from being stabbed in 1996.",
            "correct_answer": "False",
            "incorrect_answers": [
                "True"
            ]
        }
    },
    "[26, 'medium', 'any']": {
        "Question_1": {
            "type": "multiple",
            "difficulty": "medium",
            "category": "Celebrities",
            "question": "What was the name of Marilyn Monroe's first husband?",
            "correct_answer": "James Dougherty",
            "incorrect_answers": [
                "Joe Dimaggio",
                "Kirk Douglas",
                "Arthur Miller"
            ]
        },
        "Question_2": {
            "type": "multiple",
            "difficulty": "medium",
            "category": "Celebrities",
            "question": "Which actress's real name was Frances Ethel Gumm?",
            "correct_answer": "Judy Garland",
            "incorrect_answers": [
                "Doris Day",
                "Julie Andrews",
                "Marilyn Monroe"
            ]
        },
        "Question_3": {
            "type": "multiple",
            "difficulty": "medium",
            "category": "Celebrities",
            "question": "What was the cause of death for Freddie Mercury?",
            "correct_answer": "Pneumonia",
            "incorrect_answers": [
                "Stomach Cancer",
                "HIV",
                "Brain Hemorrhage"
            ]
        },
        "Question_4": {
            "type": "multiple",
            "difficulty": "medium",
            "category": "Celebrities",
            "question": "Which famous New York Yankees outfielder did Marilyn Monroe marry?",
            "correct_answer": "Joe DiMaggio",
            "incorrect_answers": [
                "Tino Martinez",
                "Babe Ruth",
                "Mason Williams"
            ]
        },
        "Question_5": {
            "type": "multiple",
            "difficulty": "medium",
            "category": "Celebrities",
            "question": "Which American celebrity died in 1977 playing golf in La Moraleja, Madrid?",
            "correct_answer": "Bing Crosby",
            "incorrect_answers": [
                "Elvis Presley",
                "Charlie Chaplin",
                "Groucho Marx"
            ]
        },
        "Question_6": {
            "type": "boolean",
            "difficulty": "medium",
            "category": "Celebrities",
            "question": "Michael Jackson had a pet python named \u2018Crusher\u2019.",
            "correct_answer": "True",
            "incorrect_answers": [
                "False"
            ]
        },
        "Question_7": {
            "type": "multiple",
            "difficulty": "medium",
            "category": "Celebrities",
            "question": "In which of these TV shows did the chef Gordon Ramsay not appear?",
            "correct_answer": "Auction Hunters",
            "incorrect_answers": [
                "Ramsay's Kitchen Nightmares",
                "Hotel Hell",
                "Hell's Kitchen"
            ]
        },
        "Question_8": {
            "type": "multiple",
            "difficulty": "medium",
            "category": "Celebrities",
            "question": "In 2014, this new top 100 rapper who featured in \"Computers\" and \"Body Dance\" was arrested in a NYPD sting for murder.",
            "correct_answer": "Bobby Shmurda",
            "incorrect_answers": [
                "DJ Snake",
                "Swae Lee",
                "Young Thug"
            ]
        },
        "Question_9": {
            "type": "multiple",
            "difficulty": "medium",
            "category": "Celebrities",
            "question": "What is Doug Walker's YouTube name?",
            "correct_answer": "The Nostalgia Critic",
            "incorrect_answers": [
                "The Angry Video Game Nerd",
                "AngryJoeShow",
                "The Cinema Snob"
            ]
        },
        "Question_10": {
            "type": "multiple",
            "difficulty": "medium",
            "category": "Celebrities",
            "question": "Before voicing Pearl in Steven Universe, Deedee Magno Hall was part of which American band?",
            "correct_answer": "The Party",
            "incorrect_answers": [
                "The Weather Girls",
                "The Pussycat Dolls",
                "The Cheetah Girls"
            ]
        },
        "Question_11": {
            "type": "multiple",
            "difficulty": "medium",
            "category": "Celebrities",
            "question": "In which situation was musician John Lennon assassinated?",
            "correct_answer": "Attempting to enter the Dakota Apartments building",
            "incorrect_answers": [
                "During an impromptu walk through Central Park",
                "Signing an autograph outside the Record Plant studio",
                "Waiting outside a music venue in Manhattan following a gig"
            ]
        },
        "Question_12": {
            "type": "multiple",
            "difficulty": "medium",
            "category": "Celebrities",
            "question": "How old was Muhammad Ali when he died?",
            "correct_answer": "74",
            "incorrect_answers": [
                "61",
                "He's still alive",
                "56"
            ]
        },
        "Question_13": {
            "type": "multiple",
            "difficulty": "medium",
            "category": "Celebrities",
            "question": "Nikki Diamond portrayed which Gladiator in the 1992 TV show \"Gladiators\"?",
            "correct_answer": "Scorpio",
            "incorrect_answers": [
                "Jet",
                "Nightshade",
                "Falcon"
            ]
        },
        "Question_14": {
            "type": "multiple",
            "difficulty": "medium",
            "category": "Celebrities",
            "question": "When was Elvis Presley born?",
            "correct_answer": "January 8, 1935",
            "incorrect_answers": [
                "December 13, 1931",
                "July 18, 1940",
                "April 17, 1938"
            ]
        },
        "Question_15": {
            "type": "multiple",
            "difficulty": "medium",
            "category": "Celebrities",
            "question": "What year did radio icon Howard Stern start a job at radio station WNBC?",
            "correct_answer": "1982",
            "incorrect_answers": [
                "1985",
                "1984",
                "1995"
            ]
        },
        "Question_16": {
            "type": "multiple",
            "difficulty": "medium",
            "category": "Celebrities",
            "question": "What is generally considered to be William Shakespeare's birth date?",
            "correct_answer": "April 23rd, 1564",
            "incorrect_answers": [
                "July 4th, 1409",
                "September 29th, 1699",
                "December 1st, 1750"
            ]
        },
        "Question_17": {
            "type": "multiple",
            "difficulty": "medium",
            "category": "Celebrities",
            "question": "What caused Jake Lloyd who played Anakin Skywalker in The Phantom Menace to quit acting?",
            "correct_answer": "Bullying",
            "incorrect_answers": [
                "Criminal Record",
                "Nomination for Worst Actor",
                "Racism"
            ]
        },
        "Question_18": {
            "type": "multiple",
            "difficulty": "medium",
            "category": "Celebrities",
            "question": "Which of these people is NOT a part of the Internet comedy group Mega64?",
            "correct_answer": "Jon Jafari",
            "incorrect_answers": [
                "Rocco Botte",
                "Derrick Acosta",
                "Shawn Chatfield"
            ]
        },
        "Question_19": {
            "type": "multiple",
            "difficulty": "medium",
            "category": "Celebrities",
            "question": "Who out of these actresses is the youngest?",
            "correct_answer": "Kiernan Shipka",
            "incorrect_answers": [
                "Ariel Winter",
                "Emma Watson",
                "Bonnie Wright"
            ]
        },
        "Question_20": {
            "type": "multiple",
            "difficulty": "medium",
            "category": "Celebrities",
            "question": "Where was Kanye West born?",
            "correct_answer": "Atlanta, Georgia",
            "incorrect_answers": [
                "Chicago, Illinois",
                "Los Angeles, California",
                "Detroit, Michigan"
            ]
        },
        "Question_21": {
            "type": "multiple",
            "difficulty": "medium",
            "category": "Celebrities",
            "question": "What year was O.J. Simpson aquitted of his murder charges?",
            "correct_answer": "1995",
            "incorrect_answers": [
                "1992",
                "1996",
                "1991"
            ]
        },
        "Question_22": {
            "type": "multiple",
            "difficulty": "medium",
            "category": "Celebrities",
            "question": "Which TV chef wrote an autobiography titled \"Humble Pie\"?",
            "correct_answer": "Gordon Ramsay",
            "incorrect_answers": [
                "Jamie Oliver",
                "Ainsley Harriott",
                "Antony Worrall Thompson"
            ]
        },
        "Question_23": {
            "type": "multiple",
            "difficulty": "medium",
            "category": "Celebrities",
            "question": "How much weight did Chris Pratt lose for his role as Star-Lord in \"Guardians of the Galaxy\"?",
            "correct_answer": "60 lbs",
            "incorrect_answers": [
                "30 lbs",
                "50 lbs",
                "70 lbs"
            ]
        },
        "Question_24": {
            "type": "multiple",
            "difficulty": "medium",
            "category": "Celebrities",
            "question": "Which television show has Dan Gheesling been on?",
            "correct_answer": "Big Brother",
            "incorrect_answers": [
                "Jeopardy",
                "Survivor",
                "The Bachelor"
            ]
        },
        "Question_25": {
            "type": "multiple",
            "difficulty": "medium",
            "category": "Celebrities",
            "question": "What is the real name of \"moot\", founder of the imageboard 4chan?",
            "correct_answer": "Christopher Poole",
            "incorrect_answers": [
                "Mark Zuckerberg",
                "Allison Harvard",
                "Catie Wayne"
            ]
        }
    },
    "[26, 'medium', 'multiple']": {
        "Question_1": {
            "type": "multiple",
            "difficulty": "medium",
            "category": "Celebrities",
            "question": "Who out of these actresses is the youngest?",
            "correct_answer": "Kiernan Shipka",
            "incorrect_answers": [
                "Ariel Winter",
                "Emma Watson",
                "Bonnie Wright"
            ]
        },
        "Question_2": {
            "type": "multiple",
            "difficulty": "medium",
            "category": "Celebrities",
            "question": "Donald J. Trump's Middle Name is...",
            "correct_answer": "John",
            "incorrect_answers": [
                "Jeff",
                "Jerald",
                "Jason"
            ]
        },
        "Question_3": {
            "type": "multiple",
            "difficulty": "medium",
            "category": "Celebrities",
            "question": "How old was Muhammad Ali when he died?",
            "correct_answer": "74",
            "incorrect_answers": [
                "61",
                "He's still alive",
                "56"
            ]
        },
        "Question_4": {
            "type": "multiple",
            "difficulty": "medium",
            "category": "Celebrities",
            "question": "Which of these celebrities was not a member of the Jackson 5?",
            "correct_answer": "Bo Jackson",
            "incorrect_answers": [
                "Tito Jackson",
                "Jermaine Jackson",
                "Marlon Jackson"
            ]
        },
        "Question_5": {
            "type": "multiple",
            "difficulty": "medium",
            "category": "Celebrities",
            "question": "What year was O.J. Simpson aquitted of his murder charges?",
            "correct_answer": "1995",
            "incorrect_answers": [
                "1992",
                "1996",
                "1991"
            ]
        },
        "Question_6": {
            "type": "multiple",
            "difficulty": "medium",
            "category": "Celebrities",
            "question": "In which of these TV shows did the chef Gordon Ramsay not appear?",
            "correct_answer": "Auction Hunters",
            "incorrect_answers": [
                "Ramsay's Kitchen Nightmares",
                "Hotel Hell",
                "Hell's Kitchen"
            ]
        },
        "Question_7": {
            "type": "multiple",
            "difficulty": "medium",
            "category": "Celebrities",
            "question": "Which of these people is NOT a part of the Internet comedy group Mega64?",
            "correct_answer": "Jon Jafari",
            "incorrect_answers": [
                "Rocco Botte",
                "Derrick Acosta",
                "Shawn Chatfield"
            ]
        },
        "Question_8": {
            "type": "multiple",
            "difficulty": "medium",
            "category": "Celebrities",
            "question": "In what year did \"Bob Ross\" die?",
            "correct_answer": "1995",
            "incorrect_answers": [
                "1986",
                "1989",
                "1997"
            ]
        },
        "Question_9": {
            "type": "multiple",
            "difficulty": "medium",
            "category": "Celebrities",
            "question": "Which television show has Dan Gheesling been on?",
            "correct_answer": "Big Brother",
            "incorrect_answers": [
                "Jeopardy",
                "Survivor",
                "The Bachelor"
            ]
        },
        "Question_10": {
            "type": "multiple",
            "difficulty": "medium",
            "category": "Celebrities",
            "question": "When was Elvis Presley born?",
            "correct_answer": "January 8, 1935",
            "incorrect_answers": [
                "December 13, 1931",
                "July 18, 1940",
                "April 17, 1938"
            ]
        },
        "Question_11": {
            "type": "multiple",
            "difficulty": "medium",
            "category": "Celebrities",
            "question": "Which American celebrity died in 1977 playing golf in La Moraleja, Madrid?",
            "correct_answer": "Bing Crosby",
            "incorrect_answers": [
                "Elvis Presley",
                "Charlie Chaplin",
                "Groucho Marx"
            ]
        },
        "Question_12": {
            "type": "multiple",
            "difficulty": "medium",
            "category": "Celebrities",
            "question": "What was the cause of death for Freddie Mercury?",
            "correct_answer": "Pneumonia",
            "incorrect_answers": [
                "Stomach Cancer",
                "HIV",
                "Brain Hemorrhage"
            ]
        },
        "Question_13": {
            "type": "multiple",
            "difficulty": "medium",
            "category": "Celebrities",
            "question": "Where was Kanye West born?",
            "correct_answer": "Atlanta, Georgia",
            "incorrect_answers": [
                "Chicago, Illinois",
                "Los Angeles, California",
                "Detroit, Michigan"
            ]
        },
        "Question_14": {
            "type": "multiple",
            "difficulty": "medium",
            "category": "Celebrities",
            "question": "What is generally considered to be William Shakespeare's birth date?",
            "correct_answer": "April 23rd, 1564",
            "incorrect_answers": [
                "July 4th, 1409",
                "September 29th, 1699",
                "December 1st, 1750"
            ]
        },
        "Question_15": {
            "type": "multiple",
            "difficulty": "medium",
            "category": "Celebrities",
            "question": "Before voicing Pearl in Steven Universe, Deedee Magno Hall was part of which American band?",
            "correct_answer": "The Party",
            "incorrect_answers": [
                "The Weather Girls",
                "The Pussycat Dolls",
                "The Cheetah Girls"
            ]
        },
        "Question_16": {
            "type": "multiple",
            "difficulty": "medium",
            "category": "Celebrities",
            "question": "What was the name of Marilyn Monroe's first husband?",
            "correct_answer": "James Dougherty",
            "incorrect_answers": [
                "Joe Dimaggio",
                "Kirk Douglas",
                "Arthur Miller"
            ]
        },
        "Question_17": {
            "type": "multiple",
            "difficulty": "medium",
            "category": "Celebrities",
            "question": "What year did radio icon Howard Stern start a job at radio station WNBC?",
            "correct_answer": "1982",
            "incorrect_answers": [
                "1985",
                "1984",
                "1995"
            ]
        },
        "Question_18": {
            "type": "multiple",
            "difficulty": "medium",
            "category": "Celebrities",
            "question": "What is the real name of \"moot\", founder of the imageboard 4chan?",
            "correct_answer": "Christopher Poole",
            "incorrect_answers": [
                "Mark Zuckerberg",
                "Allison Harvard",
                "Catie Wayne"
            ]
        },
        "Question_19": {
            "type": "multiple",
            "difficulty": "medium",
            "category": "Celebrities",
            "question": "Which famous New York Yankees outfielder did Marilyn Monroe marry?",
            "correct_answer": "Joe DiMaggio",
            "incorrect_answers": [
                "Tino Martinez",
                "Babe Ruth",
                "Mason Williams"
            ]
        },
        "Question_20": {
            "type": "multiple",
            "difficulty": "medium",
            "category": "Celebrities",
            "question": "Paul McCartney has always used his middle name. What is his real first name? ",
            "correct_answer": "James",
            "incorrect_answers": [
                "John",
                "Jack",
                "Justin"
            ]
        },
        "Question_21": {
            "type": "multiple",
            "difficulty": "medium",
            "category": "Celebrities",
            "question": "What caused Jake Lloyd who played Anakin Skywalker in The Phantom Menace to quit acting?",
            "correct_answer": "Bullying",
            "incorrect_answers": [
                "Criminal Record",
                "Nomination for Worst Actor",
                "Racism"
            ]
        },
        "Question_22": {
            "type": "multiple",
            "difficulty": "medium",
            "category": "Celebrities",
            "question": "Which actress's real name was Frances Ethel Gumm?",
            "correct_answer": "Judy Garland",
            "incorrect_answers": [
                "Doris Day",
                "Julie Andrews",
                "Marilyn Monroe"
            ]
        },
        "Question_23": {
            "type": "multiple",
            "difficulty": "medium",
            "category": "Celebrities",
            "question": "Which radio personality calls himself \"The King of All Media\"?",
            "correct_answer": "Howard Stern",
            "incorrect_answers": [
                "Rush Limbaugh",
                "Pete Tong",
                "Ryan Seacrest"
            ]
        },
        "Question_24": {
            "type": "multiple",
            "difficulty": "medium",
            "category": "Celebrities",
            "question": "Which TV chef wrote an autobiography titled \"Humble Pie\"?",
            "correct_answer": "Gordon Ramsay",
            "incorrect_answers": [
                "Jamie Oliver",
                "Ainsley Harriott",
                "Antony Worrall Thompson"
            ]
        },
        "Question_25": {
            "type": "multiple",
            "difficulty": "medium",
            "category": "Celebrities",
            "question": "What is Doug Walker's YouTube name?",
            "correct_answer": "The Nostalgia Critic",
            "incorrect_answers": [
                "The Angry Video Game Nerd",
                "AngryJoeShow",
                "The Cinema Snob"
            ]
        }
    },
    "[26, 'medium', 'boolean']": {
        "Question_1": {
            "type": "boolean",
            "difficulty": "medium",
            "category": "Celebrities",
            "question": "Michael Jackson had a pet python named \u2018Crusher\u2019.",
            "correct_answer": "True",
            "incorrect_answers": [
                "False"
            ]
        }
    },
    "[26, 'hard', 'any']": {
        "Question_1": {
            "type": "multiple",
            "difficulty": "hard",
            "category": "Celebrities",
            "question": "Which school in Surrey, England did Steve Backshall attend?",
            "correct_answer": "Collingwood College",
            "incorrect_answers": [
                "Tomlinscote School",
                "Kings International College",
                "Lyndhurst School"
            ]
        },
        "Question_2": {
            "type": "multiple",
            "difficulty": "hard",
            "category": "Celebrities",
            "question": "The eccentric natural philosopher Tycho Brahe kept what as a pet?",
            "correct_answer": "Moose",
            "incorrect_answers": [
                "Dog",
                "Bear",
                "Goat"
            ]
        },
        "Question_3": {
            "type": "boolean",
            "difficulty": "hard",
            "category": "Celebrities",
            "question": "Lady Gaga's real name is Stefani Joanne Angelina Germanotta.",
            "correct_answer": "True",
            "incorrect_answers": [
                "False"
            ]
        },
        "Question_4": {
            "type": "multiple",
            "difficulty": "hard",
            "category": "Celebrities",
            "question": "Billy Herrington is from which US state?",
            "correct_answer": "New York",
            "incorrect_answers": [
                "Arizona",
                "California",
                "Georgia"
            ]
        },
        "Question_5": {
            "type": "multiple",
            "difficulty": "hard",
            "category": "Celebrities",
            "question": "How tall is Tom Cruise?",
            "correct_answer": "5\u2032 7\u2033",
            "incorrect_answers": [
                "5\u2032 9\u2033",
                "5\u2032 4\u2033",
                "5\u2032 5\u2033"
            ]
        },
        "Question_6": {
            "type": "multiple",
            "difficulty": "hard",
            "category": "Celebrities",
            "question": "Who was Donald Trump's first wife?",
            "correct_answer": "Ivana Zeln\u00ed\u010dkov\u00e1",
            "incorrect_answers": [
                "Melania Knauss",
                "Marla Maples",
                "Nancy Davis"
            ]
        },
        "Question_7": {
            "type": "multiple",
            "difficulty": "hard",
            "category": "Celebrities",
            "question": "Gabe Newell was born in which year?",
            "correct_answer": "1962 ",
            "incorrect_answers": [
                "1970",
                "1960",
                "1972"
            ]
        },
        "Question_8": {
            "type": "multiple",
            "difficulty": "hard",
            "category": "Celebrities",
            "question": "What was the religion of famous singer \"Freddie Mercury\"?",
            "correct_answer": "Zoroastrianism",
            "incorrect_answers": [
                "Paganism",
                "Ashurism",
                "Judaism"
            ]
        }
    },
    "[26, 'hard', 'multiple']": {
        "Question_1": {
            "type": "multiple",
            "difficulty": "hard",
            "category": "Celebrities",
            "question": "Which school in Surrey, England did Steve Backshall attend?",
            "correct_answer": "Collingwood College",
            "incorrect_answers": [
                "Tomlinscote School",
                "Kings International College",
                "Lyndhurst School"
            ]
        },
        "Question_2": {
            "type": "multiple",
            "difficulty": "hard",
            "category": "Celebrities",
            "question": "Billy Herrington is from which US state?",
            "correct_answer": "New York",
            "incorrect_answers": [
                "Arizona",
                "California",
                "Georgia"
            ]
        },
        "Question_3": {
            "type": "multiple",
            "difficulty": "hard",
            "category": "Celebrities",
            "question": "How tall is Tom Cruise?",
            "correct_answer": "5\u2032 7\u2033",
            "incorrect_answers": [
                "5\u2032 9\u2033",
                "5\u2032 4\u2033",
                "5\u2032 5\u2033"
            ]
        },
        "Question_4": {
            "type": "multiple",
            "difficulty": "hard",
            "category": "Celebrities",
            "question": "Who was Donald Trump's first wife?",
            "correct_answer": "Ivana Zeln\u00ed\u010dkov\u00e1",
            "incorrect_answers": [
                "Melania Knauss",
                "Marla Maples",
                "Nancy Davis"
            ]
        },
        "Question_5": {
            "type": "multiple",
            "difficulty": "hard",
            "category": "Celebrities",
            "question": "The eccentric natural philosopher Tycho Brahe kept what as a pet?",
            "correct_answer": "Moose",
            "incorrect_answers": [
                "Dog",
                "Bear",
                "Goat"
            ]
        },
        "Question_6": {
            "type": "multiple",
            "difficulty": "hard",
            "category": "Celebrities",
            "question": "Gabe Newell was born in which year?",
            "correct_answer": "1962 ",
            "incorrect_answers": [
                "1970",
                "1960",
                "1972"
            ]
        },
        "Question_7": {
            "type": "multiple",
            "difficulty": "hard",
            "category": "Celebrities",
            "question": "What was the religion of famous singer \"Freddie Mercury\"?",
            "correct_answer": "Zoroastrianism",
            "incorrect_answers": [
                "Paganism",
                "Ashurism",
                "Judaism"
            ]
        }
    },
    "[26, 'hard', 'boolean']": {
        "Question_1": {
            "type": "boolean",
            "difficulty": "hard",
            "category": "Celebrities",
            "question": "Lady Gaga's real name is Stefani Joanne Angelina Germanotta.",
            "correct_answer": "True",
            "incorrect_answers": [
                "False"
            ]
        }
    }
}